{"title":"Circle of Trust API","version":"V1","baseUri":"http://localhost:8080/{version}","baseUriParameters":[{"name":"version","displayName":"version","typePropertyKind":"TYPE_EXPRESSION","type":"string","required":true,"enum":["V1"],"key":"version"}],"protocols":["HTTP"],"resources":[{"methods":[{"responses":[{"code":"200","body":[{"name":"text/plain","displayName":"text/plain","typePropertyKind":"TYPE_EXPRESSION","type":"any","key":"text/plain","examples":["OK"]}],"key":"200"}],"protocols":["HTTP"],"method":"get","allUriParameters":[{"name":"version","displayName":"version","typePropertyKind":"TYPE_EXPRESSION","type":"string","required":true,"enum":["V1"],"key":"version"}],"absoluteUri":"http://localhost:8080/{version}/ping","relativeUri":"/ping","baseUri":"http://localhost:8080/{version}"}],"relativeUri":"/ping","displayName":"/ping","relativeUriPathSegments":["ping"],"absoluteUri":"http://localhost:8080/{version}/ping","parentUrl":"","allUriParameters":[{"name":"version","displayName":"version","typePropertyKind":"TYPE_EXPRESSION","type":"string","required":true,"enum":["V1"],"key":"version"}]}],"namespace":"Api"}